{
	"clienteID": 27,
	"nomeCare": "Callflex",
	"nome": "Callflex",
	"cnpj": "74.220.534/0001-60",
	"inscricaoEstadual": "92.053.62-16",
	"razaoSocial": "Callflex ME",
	"website": "callflex.com.br",
	"mercado": "MONTADORA",
	"statusCliente": "ATIVO",
	"contaContabil": "CONTABIL B",
	"codigoSAP": "RMYI-B-OR8OUL3K-KNW-V-TKGET3B7GXMFJSZ",
	"siglaCliente": "FLEX",
	"trabalhaRegioes": false,
	"trabalhaClausulas": false,
	"contatos": [
		{
			"contatoID": 1,
			"contatoNome": "Briana Brooks",
			"contatoEmail": "brianabrooks@callflex.com",
			"contatoCargo": "Gerente",
			"contatoDepartmento": "Vendas",
			"contatoResponsavel": false,
			"contatoVIP": false,
			"contatoEnderecos": [
				{
					"contatoEnderecosID": 1,
					"contatoEnderecosEndereco": "Clay Street",
					"contatoEnderecosNumero": 4297,
					"contatoEnderecosComplemento": "",
					"contatoEnderecosBairro": "Lauri",
					"contatoEnderecosCEP": "84159-234",
					"contatoEnderecosLOB": "VIAGEM",
					"contatoEnderecosEstado": "ESTADO 2",
					"contatoEnderecosCidade": "CIDADE 1",
					"contatoEnderecosPais": "FRANÇA",
					"contatoEnderecosTipo": "COMERCIAL",
					"contatoEnderecosCorrespondencia": false,
					"contatoEnderecosCobranca": false
				},
				{
					"contatoEnderecosID": 2,
					"contatoEnderecosEndereco": "Navy Street",
					"contatoEnderecosNumero": 6563,
					"contatoEnderecosComplemento": "",
					"contatoEnderecosBairro": "Koch",
					"contatoEnderecosCEP": "95350-024",
					"contatoEnderecosLOB": "VIAGEM",
					"contatoEnderecosEstado": "ESTADO 3",
					"contatoEnderecosCidade": "CIDADE 3",
					"contatoEnderecosPais": "BRASIL",
					"contatoEnderecosTipo": "COMERCIAL",
					"contatoEnderecosCorrespondencia": false,
					"contatoEnderecosCobranca": false
				},
				{
					"contatoEnderecosID": 3,
					"contatoEnderecosEndereco": "Cambridge Place",
					"contatoEnderecosNumero": 2251,
					"contatoEnderecosComplemento": "",
					"contatoEnderecosBairro": "Beck",
					"contatoEnderecosCEP": "81249-929",
					"contatoEnderecosLOB": "VIAGEM",
					"contatoEnderecosEstado": "ESTADO 3",
					"contatoEnderecosCidade": "CIDADE 3",
					"contatoEnderecosPais": "BRASIL",
					"contatoEnderecosTipo": "COBRANCA",
					"contatoEnderecosCorrespondencia": true,
					"contatoEnderecosCobranca": false
				}
			],
			"contatoTelefones": [
				{
					"contatoTelefonesID": 1,
					"contatoTelefonesDDD": 71,
					"contatoTelefonesTelefone": "78615-9228",
					"contatoTelefonesRamal": ""
				},
				{
					"contatoTelefonesID": 2,
					"contatoTelefonesDDD": 81,
					"contatoTelefonesTelefone": "99624-8235",
					"contatoTelefonesRamal": ""
				}
			]
		},
		{
			"contatoID": 2,
			"contatoNome": "Daniels Dodson",
			"contatoEmail": "danielsdodson@callflex.com",
			"contatoCargo": "Assistente",
			"contatoDepartmento": "Jurídico",
			"contatoResponsavel": false,
			"contatoVIP": true,
			"contatoEnderecos": [
				{
					"contatoEnderecosID": 1,
					"contatoEnderecosEndereco": "Tapscott Street",
					"contatoEnderecosNumero": 9994,
					"contatoEnderecosComplemento": "",
					"contatoEnderecosBairro": "Twila",
					"contatoEnderecosCEP": "83648-838",
					"contatoEnderecosLOB": "AUTO",
					"contatoEnderecosEstado": "ESTADO 1",
					"contatoEnderecosCidade": "CIDADE 1",
					"contatoEnderecosPais": "FRANÇA",
					"contatoEnderecosTipo": "COBRANCA",
					"contatoEnderecosCorrespondencia": false,
					"contatoEnderecosCobranca": true
				}
			],
			"contatoTelefones": [
				{
					"contatoTelefonesID": 1,
					"contatoTelefonesDDD": 21,
					"contatoTelefonesTelefone": "3828-4902",
					"contatoTelefonesRamal": 211
				},
				{
					"contatoTelefonesID": 2,
					"contatoTelefonesDDD": 31,
					"contatoTelefonesTelefone": "4808-4543",
					"contatoTelefonesRamal": 78
				}
			]
		},
		{
			"contatoID": 3,
			"contatoNome": "Berg Hughes",
			"contatoEmail": "berghughes@callflex.com",
			"contatoCargo": "Assistente",
			"contatoDepartmento": "Financeiro",
			"contatoResponsavel": false,
			"contatoVIP": false,
			"contatoEnderecos": [
				{
					"contatoEnderecosID": 1,
					"contatoEnderecosEndereco": "Hutchinson Court",
					"contatoEnderecosNumero": 5564,
					"contatoEnderecosComplemento": "",
					"contatoEnderecosBairro": "Kristine",
					"contatoEnderecosCEP": "90446-721",
					"contatoEnderecosLOB": "FUNERAL",
					"contatoEnderecosEstado": "ESTADO 2",
					"contatoEnderecosCidade": "CIDADE 2",
					"contatoEnderecosPais": "FRANÇA",
					"contatoEnderecosTipo": "COMERCIAL",
					"contatoEnderecosCorrespondencia": false,
					"contatoEnderecosCobranca": false
				},
				{
					"contatoEnderecosID": 2,
					"contatoEnderecosEndereco": "Prospect Avenue",
					"contatoEnderecosNumero": 6505,
					"contatoEnderecosComplemento": "Loja",
					"contatoEnderecosBairro": "Donovan",
					"contatoEnderecosCEP": "87045-724",
					"contatoEnderecosLOB": "RAMOS ELEMENTARES",
					"contatoEnderecosEstado": "ESTADO 2",
					"contatoEnderecosCidade": "CIDADE 3",
					"contatoEnderecosPais": "BRASIL",
					"contatoEnderecosTipo": "COBRANCA",
					"contatoEnderecosCorrespondencia": true,
					"contatoEnderecosCobranca": true
				},
				{
					"contatoEnderecosID": 3,
					"contatoEnderecosEndereco": "Seaview Avenue",
					"contatoEnderecosNumero": 397,
					"contatoEnderecosComplemento": "",
					"contatoEnderecosBairro": "Lidia",
					"contatoEnderecosCEP": "99053-739",
					"contatoEnderecosLOB": "AUTO",
					"contatoEnderecosEstado": "ESTADO 3",
					"contatoEnderecosCidade": "CIDADE 2",
					"contatoEnderecosPais": "FRANÇA",
					"contatoEnderecosTipo": "COMERCIAL",
					"contatoEnderecosCorrespondencia": false,
					"contatoEnderecosCobranca": true
				}
			],
			"contatoTelefones": [
				{
					"contatoTelefonesID": 1,
					"contatoTelefonesDDD": 11,
					"contatoTelefonesTelefone": "89654-6331",
					"contatoTelefonesRamal": ""
				},
				{
					"contatoTelefonesID": 2,
					"contatoTelefonesDDD": 81,
					"contatoTelefonesTelefone": "6945-5382",
					"contatoTelefonesRamal": ""
				}
			]
		},
		{
			"contatoID": 4,
			"contatoNome": "Myers Olson",
			"contatoEmail": "myersolson@callflex.com",
			"contatoCargo": "Gerente",
			"contatoDepartmento": "Jurídico",
			"contatoResponsavel": true,
			"contatoVIP": false,
			"contatoEnderecos": [
				{
					"contatoEnderecosID": 1,
					"contatoEnderecosEndereco": "Suydam Street",
					"contatoEnderecosNumero": 821,
					"contatoEnderecosComplemento": "Térreo",
					"contatoEnderecosBairro": "Deena",
					"contatoEnderecosCEP": "96451-122",
					"contatoEnderecosLOB": "VIAGEM",
					"contatoEnderecosEstado": "ESTADO 2",
					"contatoEnderecosCidade": "CIDADE 2",
					"contatoEnderecosPais": "BRASIL",
					"contatoEnderecosTipo": "COMERCIAL",
					"contatoEnderecosCorrespondencia": true,
					"contatoEnderecosCobranca": false
				},
				{
					"contatoEnderecosID": 2,
					"contatoEnderecosEndereco": "Columbus Place",
					"contatoEnderecosNumero": 5494,
					"contatoEnderecosComplemento": "Térreo",
					"contatoEnderecosBairro": "Trina",
					"contatoEnderecosCEP": "94444-428",
					"contatoEnderecosLOB": "FUNERAL",
					"contatoEnderecosEstado": "ESTADO 3",
					"contatoEnderecosCidade": "CIDADE 1",
					"contatoEnderecosPais": "FRANÇA",
					"contatoEnderecosTipo": "COMERCIAL",
					"contatoEnderecosCorrespondencia": false,
					"contatoEnderecosCobranca": true
				}
			],
			"contatoTelefones": [
				{
					"contatoTelefonesID": 1,
					"contatoTelefonesDDD": 81,
					"contatoTelefonesTelefone": "4808-4532",
					"contatoTelefonesRamal": ""
				}
			]
		},
		{
			"contatoID": 5,
			"contatoNome": "Rhonda Bender",
			"contatoEmail": "rhondabender@callflex.com",
			"contatoCargo": "Assistente",
			"contatoDepartmento": "Vendas",
			"contatoResponsavel": false,
			"contatoVIP": false,
			"contatoEnderecos": [
				{
					"contatoEnderecosID": 1,
					"contatoEnderecosEndereco": "Georgia Avenue",
					"contatoEnderecosNumero": 7194,
					"contatoEnderecosComplemento": "",
					"contatoEnderecosBairro": "Cora",
					"contatoEnderecosCEP": "90456-838",
					"contatoEnderecosLOB": "AUTO",
					"contatoEnderecosEstado": "ESTADO 1",
					"contatoEnderecosCidade": "CIDADE 1",
					"contatoEnderecosPais": "BRASIL",
					"contatoEnderecosTipo": "COMERCIAL",
					"contatoEnderecosCorrespondencia": false,
					"contatoEnderecosCobranca": false
				}
			],
			"contatoTelefones": [
				{
					"contatoTelefonesID": 1,
					"contatoTelefonesDDD": 21,
					"contatoTelefonesTelefone": "4855-5223",
					"contatoTelefonesRamal": 192
				}
			]
		},
		{
			"contatoID": 6,
			"contatoNome": "Mason Boyer",
			"contatoEmail": "masonboyer@callflex.com",
			"contatoCargo": "Assistente",
			"contatoDepartmento": "Jurídico",
			"contatoResponsavel": false,
			"contatoVIP": true,
			"contatoEnderecos": [
				{
					"contatoEnderecosID": 1,
					"contatoEnderecosEndereco": "Ryder Avenue",
					"contatoEnderecosNumero": 2399,
					"contatoEnderecosComplemento": "Loja",
					"contatoEnderecosBairro": "Gwen",
					"contatoEnderecosCEP": "84152-239",
					"contatoEnderecosLOB": "AUTO",
					"contatoEnderecosEstado": "ESTADO 1",
					"contatoEnderecosCidade": "CIDADE 1",
					"contatoEnderecosPais": "FRANÇA",
					"contatoEnderecosTipo": "COBRANCA",
					"contatoEnderecosCorrespondencia": true,
					"contatoEnderecosCobranca": true
				},
				{
					"contatoEnderecosID": 2,
					"contatoEnderecosEndereco": "Bushwick Avenue",
					"contatoEnderecosNumero": 6912,
					"contatoEnderecosComplemento": "Loja",
					"contatoEnderecosBairro": "Catherine",
					"contatoEnderecosCEP": "87153-233",
					"contatoEnderecosLOB": "VIAGEM",
					"contatoEnderecosEstado": "ESTADO 1",
					"contatoEnderecosCidade": "CIDADE 3",
					"contatoEnderecosPais": "BRASIL",
					"contatoEnderecosTipo": "COMERCIAL",
					"contatoEnderecosCorrespondencia": false,
					"contatoEnderecosCobranca": false
				}
			],
			"contatoTelefones": [
				{
					"contatoTelefonesID": 1,
					"contatoTelefonesDDD": 11,
					"contatoTelefonesTelefone": "78955-6037",
					"contatoTelefonesRamal": ""
				}
			]
		},
		{
			"contatoID": 7,
			"contatoNome": "Dunn Ferguson",
			"contatoEmail": "dunnferguson@callflex.com",
			"contatoCargo": "Assistente",
			"contatoDepartmento": "Financeiro",
			"contatoResponsavel": true,
			"contatoVIP": true,
			"contatoEnderecos": [
				{
					"contatoEnderecosID": 1,
					"contatoEnderecosEndereco": "Lake Avenue",
					"contatoEnderecosNumero": 3478,
					"contatoEnderecosComplemento": "",
					"contatoEnderecosBairro": "Bertie",
					"contatoEnderecosCEP": "81054-439",
					"contatoEnderecosLOB": "RAMOS ELEMENTARES",
					"contatoEnderecosEstado": "ESTADO 3",
					"contatoEnderecosCidade": "CIDADE 3",
					"contatoEnderecosPais": "BRASIL",
					"contatoEnderecosTipo": "COBRANCA",
					"contatoEnderecosCorrespondencia": false,
					"contatoEnderecosCobranca": true
				},
				{
					"contatoEnderecosID": 2,
					"contatoEnderecosEndereco": "Lincoln Road",
					"contatoEnderecosNumero": 3355,
					"contatoEnderecosComplemento": "",
					"contatoEnderecosBairro": "Corrine",
					"contatoEnderecosCEP": "94649-421",
					"contatoEnderecosLOB": "VIAGEM",
					"contatoEnderecosEstado": "ESTADO 1",
					"contatoEnderecosCidade": "CIDADE 1",
					"contatoEnderecosPais": "FRANÇA",
					"contatoEnderecosTipo": "COMERCIAL",
					"contatoEnderecosCorrespondencia": false,
					"contatoEnderecosCobranca": true
				}
			],
			"contatoTelefones": [
				{
					"contatoTelefonesID": 1,
					"contatoTelefonesDDD": 81,
					"contatoTelefonesTelefone": "98444-7239",
					"contatoTelefonesRamal": ""
				}
			]
		}
	],
	"regioes": [
		{
			"regioesID": 1,
			"regioesCodigo": "irure",
			"regioesDescricao": "Aliqua veniam ut laborum labore fugiat dolor."
		}
	],
	"arquivos": [
		{
			"arquivosID": 1,
			"arquivosPath": "/userfiles/commodo.docx",
			"arquivosDescricao": "Et labore qui non mollit in elit ullamco ut id.",
			"arquivosDataCriacao": "2022-11-17 18:33:51",
			"arquivosFileSize": 2288012
		},
		{
			"arquivosID": 2,
			"arquivosPath": "/userfiles/proident.xlsx",
			"arquivosDescricao": "Est qui reprehenderit cillum enim adipisicing sunt nulla laborum.",
			"arquivosDataCriacao": "2022-01-06 13:56:19",
			"arquivosFileSize": 1985040
		},
		{
			"arquivosID": 3,
			"arquivosPath": "/userfiles/laboris.pdf",
			"arquivosDescricao": "Adipisicing duis eiusmod nulla deserunt esse sint non exercitation quis.",
			"arquivosDataCriacao": "2022-03-16 13:31:33",
			"arquivosFileSize": 722409
		},
		{
			"arquivosID": 4,
			"arquivosPath": "/userfiles/enim.xlsx",
			"arquivosDescricao": "Laborum amet aliqua deserunt ullamco est excepteur id duis anim amet eu mollit.",
			"arquivosDataCriacao": "2022-07-15 16:41:31",
			"arquivosFileSize": 2694294
		}
	],
	"contratos": [
		{
			"contratosID": 1,
			"contratosNome": "aliquip commodo",
			"contratoLOBPrincipal": [
				"RA",
				"RAMOS ELEMENTARES"
			],
			"contratoInicioVigencia": "2019-09-07",
			"contratoFimVigencia": "2025-01-01",
			"contratoInformacoes": "INFORMAÇÕES GERAIS",
			"contratoComentario": "Excepteur labore consectetur ut et incididunt aute aliqua aute exercitation nisi elit. Non occaecat voluptate laboris deserunt cillum consectetur nostrud sunt sit fugiat anim sint fugiat ea.",
			"contratoInicioAtividades": "2019-09-08",
			"contratoLOBSecundarios": [
				{
					"contratoLOBSecundariosID": 1,
					"contratoLOBSecundariosLOB": [
						"VI",
						"VIAGEM"
					]
				},
				{
					"contratoLOBSecundariosID": 2,
					"contratoLOBSecundariosLOB": [
						"RA",
						"RAMOS ELEMENTARES"
					]
				},
				{
					"contratoLOBSecundariosID": 3,
					"contratoLOBSecundariosLOB": [
						"RA",
						"RAMOS ELEMENTARES"
					]
				}
			]
		},
		{
			"contratosID": 2,
			"contratosNome": "sint aliqua",
			"contratoLOBPrincipal": [
				"AU",
				"AUTO"
			],
			"contratoInicioVigencia": "2020-09-16",
			"contratoFimVigencia": "2025-01-01",
			"contratoInformacoes": "INFORMAÇÕES COMPLEMENTARES",
			"contratoComentario": "Quis tempor anim velit velit aliqua non Lorem deserunt duis non excepteur reprehenderit nisi velit. Eu officia est commodo velit et cillum aliqua.",
			"contratoInicioAtividades": "2020-09-17",
			"contratoLOBSecundarios": [
				{
					"contratoLOBSecundariosID": 1,
					"contratoLOBSecundariosLOB": [
						"AU",
						"AUTO"
					]
				},
				{
					"contratoLOBSecundariosID": 2,
					"contratoLOBSecundariosLOB": [
						"FU",
						"FUNERAL"
					]
				},
				{
					"contratoLOBSecundariosID": 3,
					"contratoLOBSecundariosLOB": [
						"RA",
						"RAMOS ELEMENTARES"
					]
				}
			]
		},
		{
			"contratosID": 3,
			"contratosNome": "magna in",
			"contratoLOBPrincipal": [
				"FU",
				"FUNERAL"
			],
			"contratoInicioVigencia": "2022-05-18",
			"contratoFimVigencia": "2025-01-01",
			"contratoInformacoes": "INFORMAÇÕES GERAIS",
			"contratoComentario": "Dolore exercitation in id dolor. Nisi in dolor mollit pariatur esse deserunt veniam sit reprehenderit nulla proident deserunt.",
			"contratoInicioAtividades": "2022-05-19",
			"contratoLOBSecundarios": [
				{
					"contratoLOBSecundariosID": 1,
					"contratoLOBSecundariosLOB": [
						"RA",
						"RAMOS ELEMENTARES"
					]
				}
			]
		},
		{
			"contratosID": 4,
			"contratosNome": "eiusmod amet",
			"contratoLOBPrincipal": [
				"RA",
				"RAMOS ELEMENTARES"
			],
			"contratoInicioVigencia": "2019-09-04",
			"contratoFimVigencia": "2025-01-01",
			"contratoInformacoes": "INFORMAÇÕES GERAIS",
			"contratoComentario": "Consectetur ad magna irure elit magna duis aliquip ex aute consectetur. Aliqua deserunt non pariatur excepteur enim qui consectetur consequat anim.",
			"contratoInicioAtividades": "2019-09-05",
			"contratoLOBSecundarios": [
				{
					"contratoLOBSecundariosID": 1,
					"contratoLOBSecundariosLOB": [
						"AU",
						"AUTO"
					]
				}
			]
		},
		{
			"contratosID": 5,
			"contratosNome": "nostrud in",
			"contratoLOBPrincipal": [
				"FU",
				"FUNERAL"
			],
			"contratoInicioVigencia": "2020-11-24",
			"contratoFimVigencia": "2025-01-01",
			"contratoInformacoes": "INFORMAÇÕES GERAIS",
			"contratoComentario": "Cillum commodo ut deserunt aliquip mollit sint do excepteur fugiat fugiat. Duis consectetur sunt aliquip magna nisi voluptate sint deserunt.",
			"contratoInicioAtividades": "2020-11-25",
			"contratoLOBSecundarios": [
				{
					"contratoLOBSecundariosID": 1,
					"contratoLOBSecundariosLOB": [
						"AU",
						"AUTO"
					]
				}
			]
		}
	]
}